vcardz/__init__.py
vcardz/atom.py
vcardz/bag.py
vcardz/builder.py
vcardz/data.py
vcardz/errors.py
vcardz/google.py
vcardz/log.py
vcardz/outlook.py
vcardz/parse.py
vcardz/pst.py
vcardz/tag.py
vcardz/utils.py
vcardz/vcard.py
vcardz_data-0.9.2.dist-info/DESCRIPTION.rst
vcardz_data-0.9.2.dist-info/METADATA
vcardz_data-0.9.2.dist-info/RECORD
vcardz_data-0.9.2.dist-info/WHEEL
vcardz_data-0.9.2.dist-info/metadata.json
vcardz_data-0.9.2.dist-info/top_level.txt
